odoo/addons/stock_report_quantity_by_location/README.rst
odoo/addons/stock_report_quantity_by_location/__init__.py
odoo/addons/stock_report_quantity_by_location/__manifest__.py
odoo/addons/stock_report_quantity_by_location/i18n/stock_report_quantity_by_location.pot
odoo/addons/stock_report_quantity_by_location/readme/CONTRIBUTORS.rst
odoo/addons/stock_report_quantity_by_location/readme/DESCRIPTION.rst
odoo/addons/stock_report_quantity_by_location/static/description/icon.png
odoo/addons/stock_report_quantity_by_location/static/description/index.html
odoo/addons/stock_report_quantity_by_location/tests/__init__.py
odoo/addons/stock_report_quantity_by_location/tests/test_stock_report_quantity_by_location.py
odoo/addons/stock_report_quantity_by_location/wizards/__init__.py
odoo/addons/stock_report_quantity_by_location/wizards/stock_report_quantity_by_location.py
odoo/addons/stock_report_quantity_by_location/wizards/stock_report_quantity_by_location_views.xml
odoo11_addon_stock_report_quantity_by_location-11.0.1.0.0.99.dev6.dist-info/METADATA
odoo11_addon_stock_report_quantity_by_location-11.0.1.0.0.99.dev6.dist-info/WHEEL
odoo11_addon_stock_report_quantity_by_location-11.0.1.0.0.99.dev6.dist-info/top_level.txt
odoo11_addon_stock_report_quantity_by_location-11.0.1.0.0.99.dev6.dist-info/RECORD
